steno/__init__.py
verysteno-1.0.0.dist-info/METADATA
verysteno-1.0.0.dist-info/WHEEL
verysteno-1.0.0.dist-info/top_level.txt
verysteno-1.0.0.dist-info/RECORD
