Metadata-Version: 2.2
Name: verysteno
Version: 1.0.0
Summary: A library for encoding and decoding messages in sound and images using steganography.
Home-page: https://github.com/XenonPy/steno
Author: XenonPy
Author-email: xenonpy@wearehackerone.com
Classifier: Programming Language :: Python :: 3
Classifier: License :: OSI Approved :: MIT License
Classifier: Operating System :: OS Independent
Requires-Python: >=3.7
Requires-Dist: numpy
Requires-Dist: pillow
Dynamic: author
Dynamic: author-email
Dynamic: classifier
Dynamic: description
Dynamic: description-content-type
Dynamic: home-page
Dynamic: requires-dist
Dynamic: requires-python
Dynamic: summary
